LICENSE
MANIFEST.in
README.md
setup.py
pyhelix/__init__.py
pyhelix/accessor.py
pyhelix/constants.py
pyhelix/helixexec.py
pyhelix/helixtask.py
pyhelix/keybuilder.py
pyhelix/participant.py
pyhelix/spectator.py
pyhelix/statemodel.py
pyhelix/znode.py
pyhelix.egg-info/PKG-INFO
pyhelix.egg-info/SOURCES.txt
pyhelix.egg-info/dependency_links.txt
pyhelix.egg-info/not-zip-safe
pyhelix.egg-info/requires.txt
pyhelix.egg-info/top_level.txt
pyhelix/examples/__init__.py
pyhelix/examples/coderunner/__init__.py
pyhelix/examples/coderunner/coderunner.py
pyhelix/examples/coderunner/coderunner_node.py
pyhelix/examples/coderunner/runnermodel.py
pyhelix/examples/dummy/__init__.py
pyhelix/examples/dummy/dummy_participant.py
pyhelix/examples/dummy/dummy_spectator.py
pyhelix/examples/dummy/dummy_statemodel.py
tests/__init__.py
tests/mockclient.py
tests/testexecutor.py
tests/testmockclient.py
tests/testparticipant.py
tests/teststatemodelparser.py