Metadata-Version: 1.1
Name: pyhelix
Version: 0.4
Summary: Python bindings for Apache Helix
Home-page: http://github.com/kanakb/pyhelix
Author: Kanak Biscuitwala, Zhen Zhang
Author-email: kanak.b@hotmail.com, nehzgnahz@gmail.com
License: Apache License 2.0
Keywords: helix
Platform: UNKNOWN
Classifier: Development Status :: 3 - Alpha
Classifier: Intended Audience :: Developers
Classifier: Intended Audience :: System Administrators
Classifier: License :: OSI Approved :: Apache Software License
Classifier: Programming Language :: Python :: 2.6
